{
    "title": "宽高比计算器 - 屏幕和图像尺寸",
    "description": "免费宽高比计算器。计算缺失尺寸，按比例调整图像大小，查找屏幕和视频的常见宽高比。",
    "keywords": "宽高比计算器, 屏幕比例, 图像缩放计算, 16:9计算器, 视频尺寸",
    "canonical": "https://calc.tools/zh/aspect-ratio/",
    "h1": "宽高比计算器",
    "intro": "计算宽高比并找到缺失尺寸。输入宽度和高度，或输入一个尺寸和比例来计算另一个。",
    "faq": [
        {"q": "什么是宽高比？", "a": "宽高比是宽度和高度之间的比例关系。常见比例包括16:9（宽屏）、4:3（标准）和1:1（正方形）。"},
        {"q": "1920x1080的宽高比是多少？", "a": "1920×1080的宽高比为16:9，这是HD和Full HD显示器及大多数视频内容的标准。"},
        {"q": "调整大小时如何保持宽高比？", "a": "将两个尺寸乘以或除以相同的系数。本计算器自动完成——输入一个尺寸和比例即可。"}
    ]
}
